<?xml version="1.0" encoding="utf-8"?>
<annotation>
   <object>
      <name>human</name>
      <pose>unspecified</pose>
      <truncated>0</truncated>
      <difficult>0</difficult>
      <bndbox>
         <xmin>1453</xmin>
         <xmax>1495</xmax>
         <ymin>2624</ymin>
         <ymax>2672</ymax>
      </bndbox>
   </object>
   <object>
      <name>human</name>
      <pose>unspecified</pose>
      <truncated>0</truncated>
      <difficult>0</difficult>
      <bndbox>
         <xmin>1271</xmin>
         <xmax>1319</xmax>
         <ymin>1513</ymin>
         <ymax>1550</ymax>
      </bndbox>
   </object>
   <folder>SAR</folder>
   <filename>TRS_0023</filename>
   <source>
      <database>HERIDAL database</database>
   </source>
   <size>
      <width>4000</width>
      <height>3000</height>
      <depth>3</depth>
   </size>
   <object>
      <name>human</name>
      <pose>unspecified</pose>
      <truncated>0</truncated>
      <difficult>0</difficult>
      <bndbox>
         <xmin>2181</xmin>
         <xmax>2218</xmax>
         <ymin>2184</ymin>
         <ymax>2224</ymax>
      </bndbox>
   </object>
</annotation>