<?xml version="1.0" encoding="utf-8"?>
<annotation>
   <object>
      <name>human</name>
      <pose>unspecified</pose>
      <truncated>0</truncated>
      <difficult>0</difficult>
      <bndbox>
         <xmin>2742</xmin>
         <xmax>2794</xmax>
         <ymin>2001</ymin>
         <ymax>2078</ymax>
      </bndbox>
   </object>
   <object>
      <name>human</name>
      <pose>unspecified</pose>
      <truncated>0</truncated>
      <difficult>0</difficult>
      <bndbox>
         <xmin>2506</xmin>
         <xmax>2582</xmax>
         <ymin>1674</ymin>
         <ymax>1727</ymax>
      </bndbox>
   </object>
   <object>
      <name>human</name>
      <pose>unspecified</pose>
      <truncated>0</truncated>
      <difficult>0</difficult>
      <bndbox>
         <xmin>2812</xmin>
         <xmax>2888</xmax>
         <ymin>1422</ymin>
         <ymax>1497</ymax>
      </bndbox>
   </object>
   <object>
      <name>human</name>
      <pose>unspecified</pose>
      <truncated>0</truncated>
      <difficult>0</difficult>
      <bndbox>
         <xmin>2519</xmin>
         <xmax>2570</xmax>
         <ymin>1048</ymin>
         <ymax>1104</ymax>
      </bndbox>
   </object>
   <object>
      <name>human</name>
      <pose>unspecified</pose>
      <truncated>0</truncated>
      <difficult>0</difficult>
      <bndbox>
         <xmin>3704</xmin>
         <xmax>3812</xmax>
         <ymin>1506</ymin>
         <ymax>1558</ymax>
      </bndbox>
   </object>
   <object>
      <name>human</name>
      <pose>unspecified</pose>
      <truncated>0</truncated>
      <difficult>0</difficult>
      <bndbox>
         <xmin>3406</xmin>
         <xmax>3476</xmax>
         <ymin>2497</ymin>
         <ymax>2568</ymax>
      </bndbox>
   </object>
   <folder>SAR</folder>
   <filename>ZRI_3010</filename>
   <source>
      <database>HERIDAL database</database>
   </source>
   <size>
      <width>4000</width>
      <height>3000</height>
      <depth>3</depth>
   </size>
   <object>
      <name>human</name>
      <pose>unspecified</pose>
      <truncated>0</truncated>
      <difficult>0</difficult>
      <bndbox>
         <xmin>3487</xmin>
         <xmax>3573</xmax>
         <ymin>2525</ymin>
         <ymax>2586</ymax>
      </bndbox>
   </object>
</annotation>