<?xml version="1.0" encoding="utf-8"?>
<annotation>
   <object>
      <name>human</name>
      <pose>unspecified</pose>
      <truncated>0</truncated>
      <difficult>0</difficult>
      <bndbox>
         <xmin>506</xmin>
         <xmax>592</xmax>
         <ymin>1026</ymin>
         <ymax>1093</ymax>
      </bndbox>
   </object>
   <folder>SAR</folder>
   <filename>ZRI_3017</filename>
   <source>
      <database>HERIDAL database</database>
   </source>
   <size>
      <width>4000</width>
      <height>3000</height>
      <depth>3</depth>
   </size>
   <object>
      <name>human</name>
      <pose>unspecified</pose>
      <truncated>0</truncated>
      <difficult>0</difficult>
      <bndbox>
         <xmin>548</xmin>
         <xmax>639</xmax>
         <ymin>1023</ymin>
         <ymax>1083</ymax>
      </bndbox>
   </object>
</annotation>