<?xml version="1.0" encoding="utf-8"?>
<annotation>
   <object>
      <name>human</name>
      <pose>unspecified</pose>
      <truncated>0</truncated>
      <difficult>0</difficult>
      <bndbox>
         <xmin>1243</xmin>
         <xmax>1296</xmax>
         <ymin>1526</ymin>
         <ymax>1560</ymax>
      </bndbox>
   </object>
   <object>
      <name>human</name>
      <pose>unspecified</pose>
      <truncated>0</truncated>
      <difficult>0</difficult>
      <bndbox>
         <xmin>2167</xmin>
         <xmax>2209</xmax>
         <ymin>2162</ymin>
         <ymax>2205</ymax>
      </bndbox>
   </object>
   <folder>SAR</folder>
   <filename>TRS_0025</filename>
   <source>
      <database>HERIDAL database</database>
   </source>
   <size>
      <width>4000</width>
      <height>3000</height>
      <depth>3</depth>
   </size>
   <object>
      <name>human</name>
      <pose>unspecified</pose>
      <truncated>0</truncated>
      <difficult>0</difficult>
      <bndbox>
         <xmin>1428</xmin>
         <xmax>1470</xmax>
         <ymin>2641</ymin>
         <ymax>2687</ymax>
      </bndbox>
   </object>
</annotation>