<?xml version="1.0" encoding="utf-8"?>
<annotation>
   <object>
      <name>human</name>
      <pose>unspecified</pose>
      <truncated>0</truncated>
      <difficult>0</difficult>
      <bndbox>
         <xmin>1018</xmin>
         <xmax>1067</xmax>
         <ymin>471</ymin>
         <ymax>531</ymax>
      </bndbox>
   </object>
   <object>
      <name>human</name>
      <pose>unspecified</pose>
      <truncated>0</truncated>
      <difficult>0</difficult>
      <bndbox>
         <xmin>1133</xmin>
         <xmax>1176</xmax>
         <ymin>2408</ymin>
         <ymax>2457</ymax>
      </bndbox>
   </object>
   <object>
      <name>human</name>
      <pose>unspecified</pose>
      <truncated>0</truncated>
      <difficult>0</difficult>
      <bndbox>
         <xmin>2827</xmin>
         <xmax>2875</xmax>
         <ymin>2488</ymin>
         <ymax>2548</ymax>
      </bndbox>
   </object>
   <folder>SAR</folder>
   <filename>TRS_0041</filename>
   <source>
      <database>HERIDAL database</database>
   </source>
   <size>
      <width>4000</width>
      <height>3000</height>
      <depth>3</depth>
   </size>
   <object>
      <name>human</name>
      <pose>unspecified</pose>
      <truncated>0</truncated>
      <difficult>0</difficult>
      <bndbox>
         <xmin>2827</xmin>
         <xmax>2879</xmax>
         <ymin>2899</ymin>
         <ymax>2954</ymax>
      </bndbox>
   </object>
</annotation>