<?xml version="1.0" encoding="utf-8"?>
<annotation>
   <object>
      <name>human</name>
      <pose>unspecified</pose>
      <truncated>0</truncated>
      <difficult>0</difficult>
      <bndbox>
         <xmin>1809</xmin>
         <xmax>1840</xmax>
         <ymin>2437</ymin>
         <ymax>2486</ymax>
      </bndbox>
   </object>
   <object>
      <name>human</name>
      <pose>unspecified</pose>
      <truncated>0</truncated>
      <difficult>0</difficult>
      <bndbox>
         <xmin>1784</xmin>
         <xmax>1816</xmax>
         <ymin>2469</ymin>
         <ymax>2504</ymax>
      </bndbox>
   </object>
   <object>
      <name>human</name>
      <pose>unspecified</pose>
      <truncated>0</truncated>
      <difficult>0</difficult>
      <bndbox>
         <xmin>1738</xmin>
         <xmax>1768</xmax>
         <ymin>2501</ymin>
         <ymax>2539</ymax>
      </bndbox>
   </object>
   <object>
      <name>human</name>
      <pose>unspecified</pose>
      <truncated>0</truncated>
      <difficult>0</difficult>
      <bndbox>
         <xmin>1724</xmin>
         <xmax>1748</xmax>
         <ymin>2485</ymin>
         <ymax>2518</ymax>
      </bndbox>
   </object>
   <object>
      <name>human</name>
      <pose>unspecified</pose>
      <truncated>0</truncated>
      <difficult>0</difficult>
      <bndbox>
         <xmin>1658</xmin>
         <xmax>1692</xmax>
         <ymin>2479</ymin>
         <ymax>2526</ymax>
      </bndbox>
   </object>
   <folder>SAR</folder>
   <filename>BRA_1028</filename>
   <source>
      <database>HERIDAL database</database>
   </source>
   <size>
      <width>4000</width>
      <height>3000</height>
      <depth>3</depth>
   </size>
   <object>
      <name>human</name>
      <pose>unspecified</pose>
      <truncated>0</truncated>
      <difficult>0</difficult>
      <bndbox>
         <xmin>1704</xmin>
         <xmax>1730</xmax>
         <ymin>2511</ymin>
         <ymax>2538</ymax>
      </bndbox>
   </object>
</annotation>